weatheasy/__init__.py
weatheasy/__main__.py
weatheasy/const.py
weatheasy/download.py
weatheasy/error.py
weatheasy/util.py
weatheasy/version.py
weatheasy/web/__init__.py
weatheasy/web/config.py
weatheasy/web/controller.py
weatheasy/web/models.py
weatheasy-0.2.2.dist-info/LICENSE
weatheasy-0.2.2.dist-info/METADATA
weatheasy-0.2.2.dist-info/WHEEL
weatheasy-0.2.2.dist-info/top_level.txt
weatheasy-0.2.2.dist-info/RECORD
