Metadata-Version: 2.1
Name: weatheasy
Version: 0.2.2
Summary: A service for easy weather data acquiring
Author-email: Margarita Usacheva <usa4eva.m@mail.ru>, Petr Tsymbarovich <petr@tsymbarovich.ru>
Project-URL: Homepage, https://github.com/AgroDT/WeathEasy
Project-URL: Repository, https://github.com/AgroDT/WeathEasy.git
Project-URL: Issues, https://github.com/AgroDT/WeathEasy/issues
Classifier: License :: OSI Approved :: MIT License
Requires-Python: >=3.12
License-File: LICENSE
Requires-Dist: netcdf4~=1.7
Requires-Dist: rasterio~=1.3
Requires-Dist: requests~=2.32
Requires-Dist: zarr~=2.18
Provides-Extra: s3
Requires-Dist: s3fs~=2024.6; extra == "s3"
Provides-Extra: web
Requires-Dist: fastapi-slim~=0.111; extra == "web"
Requires-Dist: pydantic-settings~=2.3; extra == "web"
Requires-Dist: uvicorn~=0.30; extra == "web"
